{
  "name": "image-drop",
  "title": "ImageDrop",
  "description": "<p>Allows dropping Journal Entry to the canvas as Tile</p>",
  "version": "1.0.2",
  "author": "U~man",
  "scripts": [],
  "esmodules": [
    "drop.js"
  ],
  "styles": [],
  "packs": [],
  "languages": [],
  "url": "https://gitlab.com/mesfoliesludiques/foundryvtt-image-drop",
  "manifest": "https://gitlab.com/mesfoliesludiques/foundryvtt-image-drop/-/raw/master/module.json",
  "download": "https://gitlab.com/mesfoliesludiques/foundryvtt-image-drop/-/archive/v1.0.2/foundryvtt-image-drop-v1.0.2.zip",
  "minimumCoreVersion": "0.6.0",
  "compatibleCoreVersion": "0.7.10"
}